animal_lib3/__init__.py
animal_lib3/animal.py
AnimalLibrary3-0.3.0.dist-info/METADATA
AnimalLibrary3-0.3.0.dist-info/WHEEL
AnimalLibrary3-0.3.0.dist-info/top_level.txt
AnimalLibrary3-0.3.0.dist-info/RECORD
