Metadata-Version: 2.1
Name: AnimalLibrary3
Version: 0.3.0
Summary: A third example animal library.
